clocking/__init__.py
clocking/cli.py
clocking/core.py
clocking/exception.py
clocking/util.py
clocking-0.1.2.dist-info/LICENSE.md
clocking-0.1.2.dist-info/METADATA
clocking-0.1.2.dist-info/WHEEL
clocking-0.1.2.dist-info/entry_points.txt
clocking-0.1.2.dist-info/top_level.txt
clocking-0.1.2.dist-info/RECORD
