Metadata-Version: 2.1
Name: clocking
Version: 0.1.2
Summary: Track the worked time.
Author-email: Matteo Guadrini <matteo.guadrini@hotmail.it>
Maintainer-email: Matteo Guadrini <matteo.guadrini@hotmail.it>
License: GNU General Public License v3.0
Project-URL: homepage, https://github.com/MatteoGuadrini/clocking
Project-URL: documentation, https://clocking.readthedocs.io/en/latest/
Project-URL: repository, https://github.com/MatteoGuadrini/clocking.git
Project-URL: changelog, https://github.com/MatteoGuadrini/clocking/blob/master/CHANGES.md
Keywords: track,worked,time,stamp,mark
Classifier: Programming Language :: Python :: 3
Classifier: License :: OSI Approved :: GNU General Public License v3 (GPLv3)
Classifier: Operating System :: OS Independent
Requires-Python: >=3.9
License-File: LICENSE.md
Requires-Dist: prettytable
